{
  "instrument" : "JWST/NIRSpec",
  "name" : "M33-topright-golden",
  "aperturePA" : 210.0,
  "theta" : 90.0,
  "description" : "Plan Name: M33-topright-golden\nPrimaries: target (8297 sources)\nFillers: filler (6468 sources)\nAperture PA: 210.0 Degrees\nTheta: Optional.empty\nSlitlet: 1 Shutter Slitlet, Minimum Throughput Allowed: Constrained\nNod in Slitlet: no\nNumber of Nods: 1\nDither Type: Fixed Dither\nPattern: (0,0)(1,0)(2,1)(5,1)(6,2)(7,2)\nGratings/Filters: [G140H/F100LP]\nMultiple Sources Per Row: false\nSearch Area Center: RA: 01 33 59.0579 Dec: +30 46 56.01\nSearch Area Width: 660.0 Arcseconds\nSearch Area Height: 600.0 Arcseconds\nSearch Step Size: 30.0 Arcseconds \nUse Weights: false\nEnable Monte-Carlo: false\nMonte-Carlo Shuffles: 10\nNumber of Configurations: 6\nSpectral Overlap Shutter Offset File: jwst-nirspec-g140h\nSpectral Overlap Threshold: 1.5\n\n",
  "catalog" : {
    "name" : "M33-MAIN-TOPRIGHT-GOLDEN",
    "primariesName" : "target",
    "fillersName" : "filler",
    "primaries" : null,
    "fillers" : null
  },
  "referencePointing" : {
    "ra" : 23.498395460291448,
    "dec" : 30.771738604958117
  },
  "configs" : [ {
    "name" : "c1",
    "version" : "PRDAPTSOC-058-003",
    "masterBackground" : false,
    "slitlets" : [ {
      "q" : 1,
      "d" : 20,
      "s" : 169
    }, {
      "q" : 1,
      "d" : 28,
      "s" : 51
    }, {
      "q" : 2,
      "d" : 31,
      "s" : 78
    }, {
      "q" : 2,
      "d" : 48,
      "s" : 88
    }, {
      "q" : 2,
      "d" : 54,
      "s" : 12
    }, {
      "q" : 1,
      "d" : 56,
      "s" : 149
    }, {
      "q" : 1,
      "d" : 83,
      "s" : 74
    }, {
      "q" : 1,
      "d" : 86,
      "s" : 38
    }, {
      "q" : 2,
      "d" : 95,
      "s" : 86
    }, {
      "q" : 2,
      "d" : 105,
      "s" : 52
    }, {
      "q" : 2,
      "d" : 112,
      "s" : 76
    }, {
      "q" : 2,
      "d" : 117,
      "s" : 64
    }, {
      "q" : 1,
      "d" : 124,
      "s" : 97
    }, {
      "q" : 1,
      "d" : 128,
      "s" : 20
    }, {
      "q" : 2,
      "d" : 128,
      "s" : 138
    }, {
      "q" : 2,
      "d" : 130,
      "s" : 84
    }, {
      "q" : 2,
      "d" : 139,
      "s" : 122
    }, {
      "q" : 1,
      "d" : 142,
      "s" : 112
    }, {
      "q" : 1,
      "d" : 146,
      "s" : 49
    }, {
      "q" : 1,
      "d" : 147,
      "s" : 63
    }, {
      "q" : 1,
      "d" : 150,
      "s" : 151
    }, {
      "q" : 1,
      "d" : 154,
      "s" : 135
    }, {
      "q" : 1,
      "d" : 155,
      "s" : 85
    }, {
      "q" : 2,
      "d" : 155,
      "s" : 80
    }, {
      "q" : 2,
      "d" : 156,
      "s" : 54
    }, {
      "q" : 2,
      "d" : 159,
      "s" : 148
    }, {
      "q" : 1,
      "d" : 163,
      "s" : 45
    }, {
      "q" : 2,
      "d" : 165,
      "s" : 35
    }, {
      "q" : 2,
      "d" : 165,
      "s" : 127
    }, {
      "q" : 1,
      "d" : 169,
      "s" : 77
    }, {
      "q" : 2,
      "d" : 184,
      "s" : 82
    }, {
      "q" : 2,
      "d" : 196,
      "s" : 69
    }, {
      "q" : 1,
      "d" : 199,
      "s" : 121
    }, {
      "q" : 2,
      "d" : 205,
      "s" : 42
    }, {
      "q" : 2,
      "d" : 206,
      "s" : 124
    }, {
      "q" : 2,
      "d" : 213,
      "s" : 58
    }, {
      "q" : 2,
      "d" : 217,
      "s" : 9
    }, {
      "q" : 1,
      "d" : 224,
      "s" : 94
    }, {
      "q" : 2,
      "d" : 232,
      "s" : 50
    }, {
      "q" : 2,
      "d" : 233,
      "s" : 44
    }, {
      "q" : 1,
      "d" : 236,
      "s" : 15
    }, {
      "q" : 2,
      "d" : 240,
      "s" : 74
    }, {
      "q" : 2,
      "d" : 240,
      "s" : 120
    }, {
      "q" : 1,
      "d" : 247,
      "s" : 165
    }, {
      "q" : 2,
      "d" : 260,
      "s" : 20
    }, {
      "q" : 2,
      "d" : 273,
      "s" : 6
    }, {
      "q" : 2,
      "d" : 274,
      "s" : 101
    }, {
      "q" : 1,
      "d" : 279,
      "s" : 52
    }, {
      "q" : 2,
      "d" : 295,
      "s" : 32
    }, {
      "q" : 2,
      "d" : 301,
      "s" : 154
    }, {
      "q" : 2,
      "d" : 341,
      "s" : 109
    }, {
      "q" : 1,
      "d" : 346,
      "s" : 110
    }, {
      "q" : 3,
      "d" : 19,
      "s" : 115
    }, {
      "q" : 3,
      "d" : 28,
      "s" : 146
    }, {
      "q" : 4,
      "d" : 35,
      "s" : 134
    }, {
      "q" : 3,
      "d" : 45,
      "s" : 56
    }, {
      "q" : 4,
      "d" : 45,
      "s" : 143
    }, {
      "q" : 3,
      "d" : 80,
      "s" : 119
    }, {
      "q" : 3,
      "d" : 84,
      "s" : 17
    }, {
      "q" : 4,
      "d" : 113,
      "s" : 48
    }, {
      "q" : 4,
      "d" : 128,
      "s" : 23
    }, {
      "q" : 4,
      "d" : 131,
      "s" : 136
    }, {
      "q" : 4,
      "d" : 132,
      "s" : 97
    }, {
      "q" : 4,
      "d" : 135,
      "s" : 156
    }, {
      "q" : 4,
      "d" : 143,
      "s" : 106
    }, {
      "q" : 3,
      "d" : 152,
      "s" : 54
    }, {
      "q" : 3,
      "d" : 160,
      "s" : 139
    }, {
      "q" : 4,
      "d" : 165,
      "s" : 152
    }, {
      "q" : 3,
      "d" : 200,
      "s" : 125
    }, {
      "q" : 4,
      "d" : 228,
      "s" : 4
    }, {
      "q" : 4,
      "d" : 235,
      "s" : 90
    }, {
      "q" : 4,
      "d" : 242,
      "s" : 112
    }, {
      "q" : 4,
      "d" : 272,
      "s" : 66
    }, {
      "q" : 3,
      "d" : 288,
      "s" : 92
    }, {
      "q" : 4,
      "d" : 288,
      "s" : 17
    }, {
      "q" : 4,
      "d" : 297,
      "s" : 1
    }, {
      "q" : 4,
      "d" : 341,
      "s" : 61
    }, {
      "q" : 4,
      "d" : 344,
      "s" : 94
    }, {
      "q" : 4,
      "d" : 348,
      "s" : 72
    }, {
      "q" : 2,
      "d" : 157,
      "s" : 62
    }, {
      "q" : 2,
      "d" : 246,
      "s" : 99
    }, {
      "q" : 1,
      "d" : 107,
      "s" : 100
    }, {
      "q" : 1,
      "d" : 28,
      "s" : 76
    }, {
      "q" : 2,
      "d" : 80,
      "s" : 37
    }, {
      "q" : 1,
      "d" : 225,
      "s" : 117
    }, {
      "q" : 2,
      "d" : 316,
      "s" : 67
    }, {
      "q" : 3,
      "d" : 96,
      "s" : 47
    }, {
      "q" : 3,
      "d" : 279,
      "s" : 114
    }, {
      "q" : 3,
      "d" : 71,
      "s" : 83
    }, {
      "q" : 3,
      "d" : 143,
      "s" : 71
    }, {
      "q" : 1,
      "d" : 352,
      "s" : 123
    }, {
      "q" : 4,
      "d" : 235,
      "s" : 114
    }, {
      "q" : 2,
      "d" : 171,
      "s" : 145
    }, {
      "q" : 2,
      "d" : 244,
      "s" : 14
    }, {
      "q" : 1,
      "d" : 51,
      "s" : 141
    }, {
      "q" : 2,
      "d" : 313,
      "s" : 129
    }, {
      "q" : 1,
      "d" : 61,
      "s" : 153
    }, {
      "q" : 1,
      "d" : 270,
      "s" : 65
    }, {
      "q" : 2,
      "d" : 291,
      "s" : 25
    }, {
      "q" : 2,
      "d" : 340,
      "s" : 104
    }, {
      "q" : 3,
      "d" : 203,
      "s" : 22
    }, {
      "q" : 3,
      "d" : 207,
      "s" : 31
    }, {
      "q" : 1,
      "d" : 114,
      "s" : 167
    }, {
      "q" : 2,
      "d" : 272,
      "s" : 158
    }, {
      "q" : 1,
      "d" : 111,
      "s" : 106
    }, {
      "q" : 1,
      "d" : 135,
      "s" : 171
    }, {
      "q" : 1,
      "d" : 205,
      "s" : 87
    }, {
      "q" : 1,
      "d" : 231,
      "s" : 67
    }, {
      "q" : 1,
      "d" : 353,
      "s" : 40
    }, {
      "q" : 1,
      "d" : 285,
      "s" : 129
    }, {
      "q" : 4,
      "d" : 258,
      "s" : 27
    }, {
      "q" : 3,
      "d" : 214,
      "s" : 58
    }, {
      "q" : 3,
      "d" : 338,
      "s" : 102
    }, {
      "q" : 4,
      "d" : 100,
      "s" : 140
    } ],
    "exposures" : [ {
      "name" : "c1e1",
      "gratingFilter" : "G140H_F100LP",
      "msaSlitlet" : "ONE_SHUTTER",
      "ra" : 23.503173695654322,
      "dec" : 30.759457909936923,
      "sourceIds" : [ 2178, 2448, 3462, 3476, 3532, 3560, 3582, 3619, 3687, 3990, 4720, 4995, 5120, 5140, 5308, 5529, 10294, 10503, 10506, 10558, 10564, 10588, 10630, 10642, 10698, 10747, 10763, 10766, 10798, 10823, 10825, 10827, 10836, 10837, 10850, 10877, 10884, 10897, 10924, 10977, 10994, 11016, 11051, 11148, 11193, 11197, 11232, 11319, 11372, 11397, 11413, 11419, 11480, 11535, 11631, 11683, 11706, 11717, 11726, 11736, 11824, 11890, 11963, 12023, 12684, 12742, 12769, 12816, 12838, 12915, 12933, 12991, 12999, 13067, 13101, 13123, 13143, 13150, 13164, 13203, 13260, 13275, 13398, 13446, 13459, 13750, 13793, 13883, 14023, 14174, 14252, 14378, 14385, 14457, 14523, 15012, 15198, 15210, 15240, 15613, 15617, 15769, 15783, 15965, 16056, 16137, 16187, 16234, 16295, 16423, 16562, 16569, 16648, 18249 ]
    } ],
    "primaryIds" : [ 2178, 3462, 3476, 3532, 3560, 3582, 3619, 3687, 4720, 4995, 5120, 5140, 5529, 10503, 10506, 10558, 10564, 10588, 10630, 10642, 10698, 10747, 10763, 10766, 10798, 10823, 10825, 10827, 10836, 10837, 10850, 10877, 10884, 10897, 10924, 10977, 10994, 11016, 11051, 11148, 11193, 11197, 11232, 11319, 11372, 11397, 11419, 11535, 12684, 12742, 12769, 12816, 12838, 12915, 12933, 12991, 12999, 13067, 13101, 13123, 13143, 13150, 13164, 13203, 13275, 13398, 13459, 13883, 14523, 15012, 15198, 15210, 15240, 15613, 15617, 15769, 15783, 16137, 16187 ],
    "fillerIds" : [ 2448, 3990, 5308, 10294, 11413, 11480, 11631, 11683, 11706, 11717, 11726, 11736, 11824, 11890, 11963, 12023, 13260, 13446, 13750, 13793, 14023, 14174, 14252, 14378, 14385, 14457, 15965, 16056, 16234, 16295, 16423, 16562, 16569, 16648, 18249 ]
  }, {
    "name" : "c2",
    "version" : "PRDAPTSOC-058-003",
    "masterBackground" : false,
    "slitlets" : [ {
      "q" : 1,
      "d" : 21,
      "s" : 169
    }, {
      "q" : 1,
      "d" : 29,
      "s" : 51
    }, {
      "q" : 2,
      "d" : 32,
      "s" : 78
    }, {
      "q" : 2,
      "d" : 49,
      "s" : 88
    }, {
      "q" : 2,
      "d" : 55,
      "s" : 12
    }, {
      "q" : 1,
      "d" : 57,
      "s" : 149
    }, {
      "q" : 1,
      "d" : 84,
      "s" : 74
    }, {
      "q" : 1,
      "d" : 87,
      "s" : 38
    }, {
      "q" : 2,
      "d" : 96,
      "s" : 86
    }, {
      "q" : 2,
      "d" : 106,
      "s" : 52
    }, {
      "q" : 2,
      "d" : 113,
      "s" : 76
    }, {
      "q" : 2,
      "d" : 118,
      "s" : 64
    }, {
      "q" : 1,
      "d" : 125,
      "s" : 97
    }, {
      "q" : 1,
      "d" : 129,
      "s" : 20
    }, {
      "q" : 2,
      "d" : 129,
      "s" : 138
    }, {
      "q" : 2,
      "d" : 131,
      "s" : 84
    }, {
      "q" : 2,
      "d" : 140,
      "s" : 122
    }, {
      "q" : 1,
      "d" : 143,
      "s" : 112
    }, {
      "q" : 1,
      "d" : 147,
      "s" : 49
    }, {
      "q" : 1,
      "d" : 148,
      "s" : 63
    }, {
      "q" : 1,
      "d" : 151,
      "s" : 151
    }, {
      "q" : 1,
      "d" : 155,
      "s" : 135
    }, {
      "q" : 1,
      "d" : 156,
      "s" : 85
    }, {
      "q" : 2,
      "d" : 156,
      "s" : 80
    }, {
      "q" : 2,
      "d" : 157,
      "s" : 54
    }, {
      "q" : 2,
      "d" : 160,
      "s" : 148
    }, {
      "q" : 1,
      "d" : 164,
      "s" : 45
    }, {
      "q" : 2,
      "d" : 166,
      "s" : 35
    }, {
      "q" : 2,
      "d" : 166,
      "s" : 127
    }, {
      "q" : 1,
      "d" : 170,
      "s" : 77
    }, {
      "q" : 2,
      "d" : 185,
      "s" : 82
    }, {
      "q" : 2,
      "d" : 197,
      "s" : 69
    }, {
      "q" : 1,
      "d" : 200,
      "s" : 121
    }, {
      "q" : 2,
      "d" : 206,
      "s" : 42
    }, {
      "q" : 2,
      "d" : 207,
      "s" : 124
    }, {
      "q" : 2,
      "d" : 214,
      "s" : 58
    }, {
      "q" : 2,
      "d" : 218,
      "s" : 9
    }, {
      "q" : 1,
      "d" : 225,
      "s" : 94
    }, {
      "q" : 2,
      "d" : 233,
      "s" : 50
    }, {
      "q" : 2,
      "d" : 234,
      "s" : 44
    }, {
      "q" : 1,
      "d" : 237,
      "s" : 15
    }, {
      "q" : 2,
      "d" : 241,
      "s" : 74
    }, {
      "q" : 2,
      "d" : 241,
      "s" : 120
    }, {
      "q" : 1,
      "d" : 248,
      "s" : 165
    }, {
      "q" : 2,
      "d" : 261,
      "s" : 20
    }, {
      "q" : 2,
      "d" : 274,
      "s" : 6
    }, {
      "q" : 2,
      "d" : 275,
      "s" : 101
    }, {
      "q" : 1,
      "d" : 280,
      "s" : 52
    }, {
      "q" : 2,
      "d" : 296,
      "s" : 32
    }, {
      "q" : 2,
      "d" : 302,
      "s" : 154
    }, {
      "q" : 2,
      "d" : 342,
      "s" : 109
    }, {
      "q" : 1,
      "d" : 347,
      "s" : 110
    }, {
      "q" : 3,
      "d" : 20,
      "s" : 115
    }, {
      "q" : 3,
      "d" : 29,
      "s" : 146
    }, {
      "q" : 4,
      "d" : 36,
      "s" : 134
    }, {
      "q" : 3,
      "d" : 46,
      "s" : 56
    }, {
      "q" : 4,
      "d" : 46,
      "s" : 143
    }, {
      "q" : 3,
      "d" : 81,
      "s" : 119
    }, {
      "q" : 3,
      "d" : 85,
      "s" : 17
    }, {
      "q" : 4,
      "d" : 114,
      "s" : 48
    }, {
      "q" : 4,
      "d" : 129,
      "s" : 23
    }, {
      "q" : 4,
      "d" : 132,
      "s" : 136
    }, {
      "q" : 4,
      "d" : 133,
      "s" : 97
    }, {
      "q" : 4,
      "d" : 136,
      "s" : 156
    }, {
      "q" : 4,
      "d" : 144,
      "s" : 106
    }, {
      "q" : 3,
      "d" : 153,
      "s" : 54
    }, {
      "q" : 3,
      "d" : 161,
      "s" : 139
    }, {
      "q" : 4,
      "d" : 166,
      "s" : 152
    }, {
      "q" : 3,
      "d" : 201,
      "s" : 125
    }, {
      "q" : 4,
      "d" : 229,
      "s" : 4
    }, {
      "q" : 4,
      "d" : 236,
      "s" : 90
    }, {
      "q" : 4,
      "d" : 243,
      "s" : 112
    }, {
      "q" : 4,
      "d" : 273,
      "s" : 66
    }, {
      "q" : 3,
      "d" : 289,
      "s" : 92
    }, {
      "q" : 4,
      "d" : 289,
      "s" : 17
    }, {
      "q" : 4,
      "d" : 298,
      "s" : 1
    }, {
      "q" : 4,
      "d" : 342,
      "s" : 61
    }, {
      "q" : 4,
      "d" : 345,
      "s" : 94
    }, {
      "q" : 4,
      "d" : 349,
      "s" : 72
    }, {
      "q" : 2,
      "d" : 158,
      "s" : 62
    }, {
      "q" : 2,
      "d" : 247,
      "s" : 99
    }, {
      "q" : 1,
      "d" : 108,
      "s" : 100
    }, {
      "q" : 1,
      "d" : 29,
      "s" : 76
    }, {
      "q" : 2,
      "d" : 81,
      "s" : 37
    }, {
      "q" : 1,
      "d" : 226,
      "s" : 117
    }, {
      "q" : 2,
      "d" : 317,
      "s" : 67
    }, {
      "q" : 3,
      "d" : 97,
      "s" : 47
    }, {
      "q" : 3,
      "d" : 280,
      "s" : 114
    }, {
      "q" : 3,
      "d" : 72,
      "s" : 83
    }, {
      "q" : 3,
      "d" : 144,
      "s" : 71
    }, {
      "q" : 1,
      "d" : 353,
      "s" : 123
    }, {
      "q" : 4,
      "d" : 236,
      "s" : 114
    }, {
      "q" : 2,
      "d" : 172,
      "s" : 145
    }, {
      "q" : 2,
      "d" : 245,
      "s" : 14
    }, {
      "q" : 1,
      "d" : 52,
      "s" : 141
    }, {
      "q" : 2,
      "d" : 314,
      "s" : 129
    }, {
      "q" : 1,
      "d" : 62,
      "s" : 153
    }, {
      "q" : 1,
      "d" : 271,
      "s" : 65
    }, {
      "q" : 2,
      "d" : 292,
      "s" : 25
    }, {
      "q" : 2,
      "d" : 341,
      "s" : 104
    }, {
      "q" : 3,
      "d" : 204,
      "s" : 22
    }, {
      "q" : 3,
      "d" : 208,
      "s" : 31
    }, {
      "q" : 2,
      "d" : 165,
      "s" : 141
    }, {
      "q" : 2,
      "d" : 273,
      "s" : 158
    }, {
      "q" : 1,
      "d" : 112,
      "s" : 106
    }, {
      "q" : 1,
      "d" : 136,
      "s" : 171
    }, {
      "q" : 1,
      "d" : 206,
      "s" : 87
    }, {
      "q" : 1,
      "d" : 232,
      "s" : 67
    }, {
      "q" : 1,
      "d" : 354,
      "s" : 40
    }, {
      "q" : 1,
      "d" : 286,
      "s" : 129
    }, {
      "q" : 4,
      "d" : 259,
      "s" : 27
    }, {
      "q" : 3,
      "d" : 215,
      "s" : 58
    }, {
      "q" : 3,
      "d" : 339,
      "s" : 102
    } ],
    "exposures" : [ {
      "name" : "c2e1",
      "gratingFilter" : "G140H_F100LP",
      "msaSlitlet" : "ONE_SHUTTER",
      "ra" : 23.503248550489648,
      "dec" : 30.759420725929047,
      "sourceIds" : [ 2178, 2448, 3462, 3476, 3532, 3560, 3582, 3619, 3687, 4720, 4995, 5120, 5140, 5308, 5529, 10294, 10503, 10506, 10558, 10564, 10588, 10630, 10642, 10698, 10747, 10763, 10766, 10798, 10823, 10825, 10827, 10836, 10837, 10850, 10877, 10884, 10897, 10924, 10977, 10994, 11016, 11051, 11148, 11193, 11197, 11232, 11319, 11372, 11380, 11397, 11413, 11419, 11480, 11535, 11631, 11683, 11706, 11717, 11736, 11824, 11890, 11963, 12023, 12684, 12742, 12769, 12816, 12838, 12915, 12933, 12991, 12999, 13067, 13101, 13123, 13143, 13150, 13164, 13203, 13260, 13275, 13398, 13446, 13459, 13750, 13793, 13883, 14023, 14174, 14252, 14378, 14385, 14457, 14523, 15012, 15198, 15210, 15240, 15272, 15613, 15617, 15769, 15783, 15965, 16056, 16137, 16187, 16234, 16295, 16423, 16562, 16569, 16648, 18249 ]
    } ],
    "primaryIds" : [ 2178, 3462, 3476, 3532, 3560, 3582, 3619, 3687, 4720, 4995, 5120, 5140, 5529, 10503, 10506, 10558, 10564, 10588, 10630, 10642, 10698, 10747, 10763, 10766, 10798, 10823, 10825, 10827, 10836, 10837, 10850, 10877, 10884, 10897, 10924, 10977, 10994, 11016, 11051, 11148, 11193, 11197, 11232, 11319, 11372, 11397, 11419, 11535, 12684, 12742, 12769, 12816, 12838, 12915, 12933, 12991, 12999, 13067, 13101, 13123, 13143, 13150, 13164, 13203, 13275, 13398, 13459, 13883, 14523, 15012, 15198, 15210, 15240, 15613, 15617, 15769, 15783, 16137, 16187 ],
    "fillerIds" : [ 2448, 5308, 10294, 11380, 11413, 11480, 11631, 11683, 11706, 11717, 11736, 11824, 11890, 11963, 12023, 13260, 13446, 13750, 13793, 14023, 14174, 14252, 14378, 14385, 14457, 15965, 16056, 16234, 16295, 16423, 16562, 16569, 16648, 18249 ]
  }, {
    "name" : "c3",
    "version" : "PRDAPTSOC-058-003",
    "masterBackground" : false,
    "slitlets" : [ {
      "q" : 1,
      "d" : 22,
      "s" : 170
    }, {
      "q" : 1,
      "d" : 30,
      "s" : 52
    }, {
      "q" : 2,
      "d" : 33,
      "s" : 79
    }, {
      "q" : 2,
      "d" : 50,
      "s" : 89
    }, {
      "q" : 2,
      "d" : 56,
      "s" : 13
    }, {
      "q" : 1,
      "d" : 58,
      "s" : 150
    }, {
      "q" : 1,
      "d" : 85,
      "s" : 75
    }, {
      "q" : 1,
      "d" : 88,
      "s" : 39
    }, {
      "q" : 2,
      "d" : 97,
      "s" : 87
    }, {
      "q" : 2,
      "d" : 107,
      "s" : 53
    }, {
      "q" : 2,
      "d" : 114,
      "s" : 77
    }, {
      "q" : 2,
      "d" : 119,
      "s" : 65
    }, {
      "q" : 1,
      "d" : 126,
      "s" : 98
    }, {
      "q" : 1,
      "d" : 130,
      "s" : 21
    }, {
      "q" : 2,
      "d" : 130,
      "s" : 139
    }, {
      "q" : 2,
      "d" : 132,
      "s" : 85
    }, {
      "q" : 2,
      "d" : 141,
      "s" : 123
    }, {
      "q" : 1,
      "d" : 144,
      "s" : 113
    }, {
      "q" : 1,
      "d" : 148,
      "s" : 50
    }, {
      "q" : 1,
      "d" : 149,
      "s" : 64
    }, {
      "q" : 1,
      "d" : 152,
      "s" : 152
    }, {
      "q" : 1,
      "d" : 156,
      "s" : 136
    }, {
      "q" : 1,
      "d" : 157,
      "s" : 86
    }, {
      "q" : 2,
      "d" : 157,
      "s" : 81
    }, {
      "q" : 2,
      "d" : 158,
      "s" : 55
    }, {
      "q" : 2,
      "d" : 161,
      "s" : 149
    }, {
      "q" : 1,
      "d" : 165,
      "s" : 46
    }, {
      "q" : 2,
      "d" : 167,
      "s" : 36
    }, {
      "q" : 2,
      "d" : 167,
      "s" : 128
    }, {
      "q" : 1,
      "d" : 171,
      "s" : 78
    }, {
      "q" : 2,
      "d" : 186,
      "s" : 83
    }, {
      "q" : 2,
      "d" : 198,
      "s" : 70
    }, {
      "q" : 1,
      "d" : 201,
      "s" : 122
    }, {
      "q" : 2,
      "d" : 207,
      "s" : 43
    }, {
      "q" : 2,
      "d" : 208,
      "s" : 125
    }, {
      "q" : 2,
      "d" : 215,
      "s" : 59
    }, {
      "q" : 2,
      "d" : 219,
      "s" : 10
    }, {
      "q" : 1,
      "d" : 226,
      "s" : 95
    }, {
      "q" : 2,
      "d" : 234,
      "s" : 51
    }, {
      "q" : 2,
      "d" : 235,
      "s" : 45
    }, {
      "q" : 1,
      "d" : 238,
      "s" : 16
    }, {
      "q" : 2,
      "d" : 242,
      "s" : 75
    }, {
      "q" : 2,
      "d" : 242,
      "s" : 121
    }, {
      "q" : 1,
      "d" : 249,
      "s" : 166
    }, {
      "q" : 2,
      "d" : 262,
      "s" : 21
    }, {
      "q" : 2,
      "d" : 275,
      "s" : 7
    }, {
      "q" : 2,
      "d" : 276,
      "s" : 102
    }, {
      "q" : 1,
      "d" : 281,
      "s" : 53
    }, {
      "q" : 2,
      "d" : 297,
      "s" : 33
    }, {
      "q" : 2,
      "d" : 303,
      "s" : 155
    }, {
      "q" : 2,
      "d" : 343,
      "s" : 110
    }, {
      "q" : 1,
      "d" : 348,
      "s" : 111
    }, {
      "q" : 3,
      "d" : 21,
      "s" : 116
    }, {
      "q" : 3,
      "d" : 30,
      "s" : 147
    }, {
      "q" : 4,
      "d" : 37,
      "s" : 135
    }, {
      "q" : 3,
      "d" : 47,
      "s" : 57
    }, {
      "q" : 4,
      "d" : 47,
      "s" : 144
    }, {
      "q" : 3,
      "d" : 82,
      "s" : 120
    }, {
      "q" : 3,
      "d" : 86,
      "s" : 18
    }, {
      "q" : 4,
      "d" : 115,
      "s" : 49
    }, {
      "q" : 4,
      "d" : 130,
      "s" : 24
    }, {
      "q" : 4,
      "d" : 133,
      "s" : 137
    }, {
      "q" : 4,
      "d" : 134,
      "s" : 98
    }, {
      "q" : 4,
      "d" : 137,
      "s" : 157
    }, {
      "q" : 4,
      "d" : 145,
      "s" : 107
    }, {
      "q" : 3,
      "d" : 154,
      "s" : 55
    }, {
      "q" : 3,
      "d" : 162,
      "s" : 140
    }, {
      "q" : 4,
      "d" : 167,
      "s" : 153
    }, {
      "q" : 3,
      "d" : 202,
      "s" : 126
    }, {
      "q" : 4,
      "d" : 230,
      "s" : 5
    }, {
      "q" : 4,
      "d" : 237,
      "s" : 91
    }, {
      "q" : 4,
      "d" : 244,
      "s" : 113
    }, {
      "q" : 4,
      "d" : 274,
      "s" : 67
    }, {
      "q" : 3,
      "d" : 290,
      "s" : 93
    }, {
      "q" : 4,
      "d" : 290,
      "s" : 18
    }, {
      "q" : 4,
      "d" : 299,
      "s" : 2
    }, {
      "q" : 4,
      "d" : 343,
      "s" : 62
    }, {
      "q" : 4,
      "d" : 346,
      "s" : 95
    }, {
      "q" : 4,
      "d" : 350,
      "s" : 73
    }, {
      "q" : 2,
      "d" : 159,
      "s" : 63
    }, {
      "q" : 2,
      "d" : 248,
      "s" : 100
    }, {
      "q" : 1,
      "d" : 109,
      "s" : 101
    }, {
      "q" : 1,
      "d" : 30,
      "s" : 77
    }, {
      "q" : 2,
      "d" : 82,
      "s" : 38
    }, {
      "q" : 1,
      "d" : 227,
      "s" : 118
    }, {
      "q" : 2,
      "d" : 318,
      "s" : 68
    }, {
      "q" : 3,
      "d" : 98,
      "s" : 48
    }, {
      "q" : 3,
      "d" : 281,
      "s" : 115
    }, {
      "q" : 3,
      "d" : 73,
      "s" : 84
    }, {
      "q" : 3,
      "d" : 145,
      "s" : 72
    }, {
      "q" : 1,
      "d" : 354,
      "s" : 124
    }, {
      "q" : 4,
      "d" : 345,
      "s" : 93
    }, {
      "q" : 4,
      "d" : 237,
      "s" : 115
    }, {
      "q" : 2,
      "d" : 101,
      "s" : 119
    }, {
      "q" : 1,
      "d" : 12,
      "s" : 146
    }, {
      "q" : 2,
      "d" : 173,
      "s" : 146
    }, {
      "q" : 2,
      "d" : 246,
      "s" : 15
    }, {
      "q" : 1,
      "d" : 53,
      "s" : 142
    }, {
      "q" : 2,
      "d" : 315,
      "s" : 130
    }, {
      "q" : 1,
      "d" : 63,
      "s" : 154
    }, {
      "q" : 2,
      "d" : 262,
      "s" : 20
    }, {
      "q" : 1,
      "d" : 251,
      "s" : 36
    }, {
      "q" : 1,
      "d" : 264,
      "s" : 62
    }, {
      "q" : 1,
      "d" : 272,
      "s" : 66
    }, {
      "q" : 1,
      "d" : 218,
      "s" : 109
    }, {
      "q" : 2,
      "d" : 293,
      "s" : 26
    }, {
      "q" : 3,
      "d" : 205,
      "s" : 23
    }, {
      "q" : 3,
      "d" : 254,
      "s" : 134
    }, {
      "q" : 3,
      "d" : 32,
      "s" : 44
    }, {
      "q" : 3,
      "d" : 186,
      "s" : 13
    }, {
      "q" : 3,
      "d" : 209,
      "s" : 32
    }, {
      "q" : 2,
      "d" : 166,
      "s" : 142
    }, {
      "q" : 3,
      "d" : 297,
      "s" : 88
    } ],
    "exposures" : [ {
      "name" : "c3e1",
      "gratingFilter" : "G140H_F100LP",
      "msaSlitlet" : "ONE_SHUTTER",
      "ra" : 23.503237899048294,
      "dec" : 30.75925629597297,
      "sourceIds" : [ 2178, 3462, 3476, 3532, 3560, 3582, 3619, 3687, 4720, 4995, 5120, 5140, 5145, 5308, 5529, 10294, 10503, 10506, 10558, 10564, 10588, 10630, 10642, 10698, 10747, 10763, 10766, 10798, 10823, 10825, 10827, 10836, 10837, 10850, 10877, 10884, 10897, 10924, 10977, 10994, 11016, 11051, 11148, 11193, 11197, 11232, 11319, 11325, 11372, 11380, 11390, 11397, 11413, 11419, 11535, 11631, 11683, 11717, 11736, 11824, 11890, 11963, 12023, 12684, 12742, 12769, 12816, 12838, 12915, 12933, 12991, 12999, 13067, 13085, 13101, 13123, 13143, 13150, 13164, 13203, 13275, 13398, 13459, 13493, 13729, 13750, 13760, 13793, 13883, 14023, 14378, 14457, 14523, 15012, 15198, 15210, 15240, 15613, 15617, 15769, 15783, 15965, 16056, 16104, 16137, 16168, 16187, 16233, 16234, 16423, 16500, 16562, 16569 ]
    } ],
    "primaryIds" : [ 2178, 3462, 3476, 3532, 3560, 3582, 3619, 3687, 4720, 4995, 5120, 5140, 5529, 10503, 10506, 10558, 10564, 10588, 10630, 10642, 10698, 10747, 10763, 10766, 10798, 10823, 10825, 10827, 10836, 10837, 10850, 10877, 10884, 10897, 10924, 10977, 10994, 11016, 11051, 11148, 11193, 11197, 11232, 11319, 11372, 11397, 11419, 11535, 12684, 12742, 12769, 12816, 12838, 12915, 12933, 12991, 12999, 13067, 13101, 13123, 13143, 13150, 13164, 13203, 13275, 13398, 13459, 13883, 14523, 15012, 15198, 15210, 15240, 15613, 15617, 15769, 15783, 16137, 16187 ],
    "fillerIds" : [ 5145, 5308, 10294, 11325, 11380, 11390, 11413, 11631, 11683, 11717, 11736, 11824, 11890, 11963, 12023, 13085, 13493, 13729, 13750, 13760, 13793, 14023, 14378, 14457, 15965, 16056, 16104, 16168, 16233, 16234, 16423, 16500, 16562, 16569 ]
  }, {
    "name" : "c4",
    "version" : "PRDAPTSOC-058-003",
    "masterBackground" : false,
    "slitlets" : [ {
      "q" : 1,
      "d" : 25,
      "s" : 170
    }, {
      "q" : 1,
      "d" : 33,
      "s" : 52
    }, {
      "q" : 2,
      "d" : 36,
      "s" : 79
    }, {
      "q" : 2,
      "d" : 53,
      "s" : 89
    }, {
      "q" : 2,
      "d" : 59,
      "s" : 13
    }, {
      "q" : 1,
      "d" : 61,
      "s" : 150
    }, {
      "q" : 1,
      "d" : 88,
      "s" : 75
    }, {
      "q" : 1,
      "d" : 91,
      "s" : 39
    }, {
      "q" : 2,
      "d" : 100,
      "s" : 87
    }, {
      "q" : 2,
      "d" : 110,
      "s" : 53
    }, {
      "q" : 2,
      "d" : 117,
      "s" : 77
    }, {
      "q" : 2,
      "d" : 122,
      "s" : 65
    }, {
      "q" : 1,
      "d" : 129,
      "s" : 98
    }, {
      "q" : 1,
      "d" : 133,
      "s" : 21
    }, {
      "q" : 2,
      "d" : 133,
      "s" : 139
    }, {
      "q" : 2,
      "d" : 135,
      "s" : 85
    }, {
      "q" : 2,
      "d" : 144,
      "s" : 123
    }, {
      "q" : 1,
      "d" : 147,
      "s" : 113
    }, {
      "q" : 1,
      "d" : 151,
      "s" : 50
    }, {
      "q" : 1,
      "d" : 152,
      "s" : 64
    }, {
      "q" : 1,
      "d" : 155,
      "s" : 152
    }, {
      "q" : 1,
      "d" : 159,
      "s" : 136
    }, {
      "q" : 1,
      "d" : 160,
      "s" : 86
    }, {
      "q" : 2,
      "d" : 160,
      "s" : 81
    }, {
      "q" : 2,
      "d" : 161,
      "s" : 55
    }, {
      "q" : 2,
      "d" : 164,
      "s" : 149
    }, {
      "q" : 1,
      "d" : 168,
      "s" : 46
    }, {
      "q" : 2,
      "d" : 170,
      "s" : 36
    }, {
      "q" : 2,
      "d" : 170,
      "s" : 128
    }, {
      "q" : 1,
      "d" : 174,
      "s" : 78
    }, {
      "q" : 2,
      "d" : 189,
      "s" : 83
    }, {
      "q" : 2,
      "d" : 201,
      "s" : 70
    }, {
      "q" : 1,
      "d" : 204,
      "s" : 122
    }, {
      "q" : 2,
      "d" : 210,
      "s" : 43
    }, {
      "q" : 2,
      "d" : 211,
      "s" : 125
    }, {
      "q" : 2,
      "d" : 218,
      "s" : 59
    }, {
      "q" : 2,
      "d" : 222,
      "s" : 10
    }, {
      "q" : 1,
      "d" : 229,
      "s" : 95
    }, {
      "q" : 2,
      "d" : 237,
      "s" : 51
    }, {
      "q" : 2,
      "d" : 238,
      "s" : 45
    }, {
      "q" : 1,
      "d" : 241,
      "s" : 16
    }, {
      "q" : 2,
      "d" : 245,
      "s" : 75
    }, {
      "q" : 2,
      "d" : 245,
      "s" : 121
    }, {
      "q" : 1,
      "d" : 252,
      "s" : 166
    }, {
      "q" : 2,
      "d" : 265,
      "s" : 21
    }, {
      "q" : 2,
      "d" : 278,
      "s" : 7
    }, {
      "q" : 2,
      "d" : 279,
      "s" : 102
    }, {
      "q" : 1,
      "d" : 284,
      "s" : 53
    }, {
      "q" : 2,
      "d" : 300,
      "s" : 33
    }, {
      "q" : 2,
      "d" : 306,
      "s" : 155
    }, {
      "q" : 2,
      "d" : 346,
      "s" : 110
    }, {
      "q" : 1,
      "d" : 351,
      "s" : 111
    }, {
      "q" : 3,
      "d" : 24,
      "s" : 116
    }, {
      "q" : 3,
      "d" : 33,
      "s" : 147
    }, {
      "q" : 4,
      "d" : 40,
      "s" : 135
    }, {
      "q" : 3,
      "d" : 50,
      "s" : 57
    }, {
      "q" : 4,
      "d" : 50,
      "s" : 144
    }, {
      "q" : 3,
      "d" : 85,
      "s" : 120
    }, {
      "q" : 3,
      "d" : 89,
      "s" : 18
    }, {
      "q" : 4,
      "d" : 118,
      "s" : 49
    }, {
      "q" : 4,
      "d" : 133,
      "s" : 24
    }, {
      "q" : 4,
      "d" : 136,
      "s" : 137
    }, {
      "q" : 4,
      "d" : 137,
      "s" : 98
    }, {
      "q" : 4,
      "d" : 140,
      "s" : 157
    }, {
      "q" : 4,
      "d" : 148,
      "s" : 107
    }, {
      "q" : 3,
      "d" : 157,
      "s" : 55
    }, {
      "q" : 3,
      "d" : 165,
      "s" : 140
    }, {
      "q" : 4,
      "d" : 170,
      "s" : 153
    }, {
      "q" : 3,
      "d" : 205,
      "s" : 126
    }, {
      "q" : 4,
      "d" : 233,
      "s" : 5
    }, {
      "q" : 4,
      "d" : 240,
      "s" : 91
    }, {
      "q" : 4,
      "d" : 247,
      "s" : 113
    }, {
      "q" : 4,
      "d" : 277,
      "s" : 67
    }, {
      "q" : 3,
      "d" : 293,
      "s" : 93
    }, {
      "q" : 4,
      "d" : 293,
      "s" : 18
    }, {
      "q" : 4,
      "d" : 302,
      "s" : 2
    }, {
      "q" : 4,
      "d" : 346,
      "s" : 62
    }, {
      "q" : 4,
      "d" : 349,
      "s" : 95
    }, {
      "q" : 4,
      "d" : 353,
      "s" : 73
    }, {
      "q" : 2,
      "d" : 162,
      "s" : 63
    }, {
      "q" : 2,
      "d" : 251,
      "s" : 100
    }, {
      "q" : 1,
      "d" : 112,
      "s" : 101
    }, {
      "q" : 1,
      "d" : 33,
      "s" : 77
    }, {
      "q" : 2,
      "d" : 85,
      "s" : 38
    }, {
      "q" : 1,
      "d" : 230,
      "s" : 118
    }, {
      "q" : 2,
      "d" : 321,
      "s" : 68
    }, {
      "q" : 3,
      "d" : 101,
      "s" : 48
    }, {
      "q" : 3,
      "d" : 284,
      "s" : 115
    }, {
      "q" : 3,
      "d" : 76,
      "s" : 84
    }, {
      "q" : 3,
      "d" : 148,
      "s" : 72
    }, {
      "q" : 1,
      "d" : 357,
      "s" : 124
    }, {
      "q" : 4,
      "d" : 348,
      "s" : 93
    }, {
      "q" : 4,
      "d" : 240,
      "s" : 115
    }, {
      "q" : 2,
      "d" : 104,
      "s" : 119
    }, {
      "q" : 1,
      "d" : 15,
      "s" : 146
    }, {
      "q" : 2,
      "d" : 176,
      "s" : 146
    }, {
      "q" : 2,
      "d" : 249,
      "s" : 15
    }, {
      "q" : 1,
      "d" : 56,
      "s" : 142
    }, {
      "q" : 2,
      "d" : 318,
      "s" : 130
    }, {
      "q" : 1,
      "d" : 66,
      "s" : 154
    }, {
      "q" : 2,
      "d" : 265,
      "s" : 20
    }, {
      "q" : 1,
      "d" : 254,
      "s" : 36
    }, {
      "q" : 1,
      "d" : 267,
      "s" : 62
    }, {
      "q" : 1,
      "d" : 275,
      "s" : 66
    }, {
      "q" : 1,
      "d" : 221,
      "s" : 109
    }, {
      "q" : 2,
      "d" : 296,
      "s" : 26
    }, {
      "q" : 3,
      "d" : 208,
      "s" : 23
    }, {
      "q" : 3,
      "d" : 257,
      "s" : 134
    }, {
      "q" : 3,
      "d" : 35,
      "s" : 44
    }, {
      "q" : 3,
      "d" : 189,
      "s" : 13
    }, {
      "q" : 2,
      "d" : 169,
      "s" : 142
    }, {
      "q" : 1,
      "d" : 196,
      "s" : 31
    }, {
      "q" : 1,
      "d" : 243,
      "s" : 159
    } ],
    "exposures" : [ {
      "name" : "c4e1",
      "gratingFilter" : "G140H_F100LP",
      "msaSlitlet" : "ONE_SHUTTER",
      "ra" : 23.503462461990672,
      "dec" : 30.759144756778287,
      "sourceIds" : [ 2178, 3462, 3476, 3532, 3560, 3582, 3619, 3687, 4720, 4995, 5120, 5140, 5145, 5308, 5529, 10294, 10503, 10506, 10558, 10564, 10588, 10630, 10642, 10698, 10747, 10763, 10766, 10798, 10823, 10825, 10827, 10836, 10837, 10850, 10877, 10884, 10897, 10924, 10977, 10994, 11016, 11051, 11148, 11193, 11197, 11232, 11319, 11325, 11372, 11380, 11390, 11397, 11413, 11419, 11535, 11631, 11683, 11717, 11736, 11824, 11890, 11963, 12023, 12684, 12742, 12769, 12816, 12838, 12915, 12933, 12991, 12999, 13067, 13085, 13101, 13123, 13143, 13150, 13164, 13203, 13275, 13398, 13459, 13493, 13729, 13745, 13750, 13760, 13793, 13883, 13974, 14023, 14378, 14457, 14523, 15012, 15198, 15210, 15240, 15613, 15617, 15769, 15783, 15965, 16056, 16104, 16137, 16168, 16187, 16234, 16423, 16500, 16569 ]
    } ],
    "primaryIds" : [ 2178, 3462, 3476, 3532, 3560, 3582, 3619, 3687, 4720, 4995, 5120, 5140, 5529, 10503, 10506, 10558, 10564, 10588, 10630, 10642, 10698, 10747, 10763, 10766, 10798, 10823, 10825, 10827, 10836, 10837, 10850, 10877, 10884, 10897, 10924, 10977, 10994, 11016, 11051, 11148, 11193, 11197, 11232, 11319, 11372, 11397, 11419, 11535, 12684, 12742, 12769, 12816, 12838, 12915, 12933, 12991, 12999, 13067, 13101, 13123, 13143, 13150, 13164, 13203, 13275, 13398, 13459, 13883, 14523, 15012, 15198, 15210, 15240, 15613, 15617, 15769, 15783, 16137, 16187 ],
    "fillerIds" : [ 5145, 5308, 10294, 11325, 11380, 11390, 11413, 11631, 11683, 11717, 11736, 11824, 11890, 11963, 12023, 13085, 13493, 13729, 13745, 13750, 13760, 13793, 13974, 14023, 14378, 14457, 15965, 16056, 16104, 16168, 16234, 16423, 16500, 16569 ]
  }, {
    "name" : "c5",
    "version" : "PRDAPTSOC-058-003",
    "masterBackground" : false,
    "slitlets" : [ {
      "q" : 1,
      "d" : 26,
      "s" : 171
    }, {
      "q" : 1,
      "d" : 34,
      "s" : 53
    }, {
      "q" : 2,
      "d" : 37,
      "s" : 80
    }, {
      "q" : 2,
      "d" : 54,
      "s" : 90
    }, {
      "q" : 2,
      "d" : 60,
      "s" : 14
    }, {
      "q" : 1,
      "d" : 62,
      "s" : 151
    }, {
      "q" : 1,
      "d" : 89,
      "s" : 76
    }, {
      "q" : 1,
      "d" : 92,
      "s" : 40
    }, {
      "q" : 2,
      "d" : 101,
      "s" : 88
    }, {
      "q" : 2,
      "d" : 111,
      "s" : 54
    }, {
      "q" : 2,
      "d" : 118,
      "s" : 78
    }, {
      "q" : 2,
      "d" : 123,
      "s" : 66
    }, {
      "q" : 1,
      "d" : 130,
      "s" : 99
    }, {
      "q" : 1,
      "d" : 134,
      "s" : 22
    }, {
      "q" : 2,
      "d" : 134,
      "s" : 140
    }, {
      "q" : 2,
      "d" : 136,
      "s" : 86
    }, {
      "q" : 2,
      "d" : 145,
      "s" : 124
    }, {
      "q" : 1,
      "d" : 148,
      "s" : 114
    }, {
      "q" : 1,
      "d" : 152,
      "s" : 51
    }, {
      "q" : 1,
      "d" : 153,
      "s" : 65
    }, {
      "q" : 1,
      "d" : 156,
      "s" : 153
    }, {
      "q" : 1,
      "d" : 160,
      "s" : 137
    }, {
      "q" : 1,
      "d" : 161,
      "s" : 87
    }, {
      "q" : 2,
      "d" : 161,
      "s" : 82
    }, {
      "q" : 2,
      "d" : 162,
      "s" : 56
    }, {
      "q" : 2,
      "d" : 165,
      "s" : 150
    }, {
      "q" : 1,
      "d" : 169,
      "s" : 47
    }, {
      "q" : 2,
      "d" : 171,
      "s" : 37
    }, {
      "q" : 2,
      "d" : 171,
      "s" : 129
    }, {
      "q" : 1,
      "d" : 175,
      "s" : 79
    }, {
      "q" : 2,
      "d" : 190,
      "s" : 84
    }, {
      "q" : 2,
      "d" : 202,
      "s" : 71
    }, {
      "q" : 1,
      "d" : 205,
      "s" : 123
    }, {
      "q" : 2,
      "d" : 211,
      "s" : 44
    }, {
      "q" : 2,
      "d" : 212,
      "s" : 126
    }, {
      "q" : 2,
      "d" : 219,
      "s" : 60
    }, {
      "q" : 2,
      "d" : 223,
      "s" : 11
    }, {
      "q" : 1,
      "d" : 230,
      "s" : 96
    }, {
      "q" : 2,
      "d" : 238,
      "s" : 52
    }, {
      "q" : 2,
      "d" : 239,
      "s" : 46
    }, {
      "q" : 1,
      "d" : 242,
      "s" : 17
    }, {
      "q" : 2,
      "d" : 246,
      "s" : 76
    }, {
      "q" : 2,
      "d" : 246,
      "s" : 122
    }, {
      "q" : 1,
      "d" : 253,
      "s" : 167
    }, {
      "q" : 2,
      "d" : 266,
      "s" : 22
    }, {
      "q" : 2,
      "d" : 279,
      "s" : 8
    }, {
      "q" : 2,
      "d" : 280,
      "s" : 103
    }, {
      "q" : 1,
      "d" : 285,
      "s" : 54
    }, {
      "q" : 2,
      "d" : 301,
      "s" : 34
    }, {
      "q" : 2,
      "d" : 307,
      "s" : 156
    }, {
      "q" : 2,
      "d" : 347,
      "s" : 111
    }, {
      "q" : 1,
      "d" : 352,
      "s" : 112
    }, {
      "q" : 3,
      "d" : 25,
      "s" : 117
    }, {
      "q" : 3,
      "d" : 34,
      "s" : 148
    }, {
      "q" : 4,
      "d" : 41,
      "s" : 136
    }, {
      "q" : 3,
      "d" : 51,
      "s" : 58
    }, {
      "q" : 4,
      "d" : 51,
      "s" : 145
    }, {
      "q" : 3,
      "d" : 86,
      "s" : 121
    }, {
      "q" : 3,
      "d" : 90,
      "s" : 19
    }, {
      "q" : 4,
      "d" : 119,
      "s" : 50
    }, {
      "q" : 4,
      "d" : 134,
      "s" : 25
    }, {
      "q" : 4,
      "d" : 137,
      "s" : 138
    }, {
      "q" : 4,
      "d" : 138,
      "s" : 99
    }, {
      "q" : 4,
      "d" : 141,
      "s" : 158
    }, {
      "q" : 4,
      "d" : 149,
      "s" : 108
    }, {
      "q" : 3,
      "d" : 158,
      "s" : 56
    }, {
      "q" : 3,
      "d" : 166,
      "s" : 141
    }, {
      "q" : 4,
      "d" : 171,
      "s" : 154
    }, {
      "q" : 3,
      "d" : 206,
      "s" : 127
    }, {
      "q" : 4,
      "d" : 234,
      "s" : 6
    }, {
      "q" : 4,
      "d" : 241,
      "s" : 92
    }, {
      "q" : 4,
      "d" : 248,
      "s" : 114
    }, {
      "q" : 4,
      "d" : 278,
      "s" : 68
    }, {
      "q" : 3,
      "d" : 294,
      "s" : 94
    }, {
      "q" : 4,
      "d" : 294,
      "s" : 19
    }, {
      "q" : 4,
      "d" : 303,
      "s" : 3
    }, {
      "q" : 4,
      "d" : 347,
      "s" : 63
    }, {
      "q" : 4,
      "d" : 350,
      "s" : 96
    }, {
      "q" : 4,
      "d" : 354,
      "s" : 74
    }, {
      "q" : 2,
      "d" : 163,
      "s" : 64
    }, {
      "q" : 2,
      "d" : 252,
      "s" : 101
    }, {
      "q" : 1,
      "d" : 113,
      "s" : 102
    }, {
      "q" : 1,
      "d" : 34,
      "s" : 78
    }, {
      "q" : 2,
      "d" : 86,
      "s" : 39
    }, {
      "q" : 1,
      "d" : 231,
      "s" : 119
    }, {
      "q" : 2,
      "d" : 322,
      "s" : 69
    }, {
      "q" : 3,
      "d" : 102,
      "s" : 49
    }, {
      "q" : 3,
      "d" : 285,
      "s" : 116
    }, {
      "q" : 3,
      "d" : 77,
      "s" : 85
    }, {
      "q" : 3,
      "d" : 149,
      "s" : 73
    }, {
      "q" : 4,
      "d" : 349,
      "s" : 94
    }, {
      "q" : 2,
      "d" : 105,
      "s" : 120
    }, {
      "q" : 1,
      "d" : 16,
      "s" : 147
    }, {
      "q" : 2,
      "d" : 266,
      "s" : 21
    }, {
      "q" : 1,
      "d" : 255,
      "s" : 37
    }, {
      "q" : 1,
      "d" : 268,
      "s" : 63
    }, {
      "q" : 1,
      "d" : 222,
      "s" : 110
    }, {
      "q" : 2,
      "d" : 346,
      "s" : 106
    }, {
      "q" : 3,
      "d" : 258,
      "s" : 135
    }, {
      "q" : 3,
      "d" : 36,
      "s" : 45
    }, {
      "q" : 3,
      "d" : 190,
      "s" : 14
    }, {
      "q" : 1,
      "d" : 120,
      "s" : 169
    }, {
      "q" : 1,
      "d" : 51,
      "s" : 31
    }, {
      "q" : 2,
      "d" : 79,
      "s" : 134
    }, {
      "q" : 1,
      "d" : 88,
      "s" : 27
    }, {
      "q" : 1,
      "d" : 163,
      "s" : 105
    }, {
      "q" : 1,
      "d" : 248,
      "s" : 159
    }, {
      "q" : 1,
      "d" : 254,
      "s" : 165
    }, {
      "q" : 3,
      "d" : 111,
      "s" : 91
    }, {
      "q" : 3,
      "d" : 335,
      "s" : 71
    } ],
    "exposures" : [ {
      "name" : "c5e1",
      "gratingFilter" : "G140H_F100LP",
      "msaSlitlet" : "ONE_SHUTTER",
      "ra" : 23.50345180747465,
      "dec" : 30.75898034846091,
      "sourceIds" : [ 2178, 3462, 3476, 3532, 3560, 3582, 3619, 3687, 4720, 4995, 5120, 5140, 5145, 5529, 10294, 10503, 10506, 10558, 10564, 10588, 10630, 10642, 10698, 10747, 10763, 10766, 10798, 10823, 10825, 10827, 10836, 10837, 10850, 10877, 10884, 10897, 10924, 10977, 10994, 11016, 11051, 11143, 11148, 11193, 11197, 11232, 11319, 11325, 11372, 11390, 11397, 11419, 11535, 11548, 11717, 11726, 11890, 11963, 12023, 12684, 12742, 12769, 12816, 12838, 12915, 12933, 12991, 12999, 13067, 13085, 13101, 13123, 13143, 13150, 13164, 13203, 13275, 13398, 13459, 13493, 13586, 13729, 13760, 13773, 13883, 13975, 14023, 14281, 14385, 14457, 14523, 15012, 15198, 15210, 15240, 15613, 15617, 15769, 15783, 15946, 16056, 16104, 16137, 16168, 16187, 16234, 16423, 16500, 16569, 18726 ]
    } ],
    "primaryIds" : [ 2178, 3462, 3476, 3532, 3560, 3582, 3619, 3687, 4720, 4995, 5120, 5140, 5529, 10503, 10506, 10558, 10564, 10588, 10630, 10642, 10698, 10747, 10763, 10766, 10798, 10823, 10825, 10827, 10836, 10837, 10850, 10877, 10884, 10897, 10924, 10977, 10994, 11016, 11051, 11148, 11193, 11197, 11232, 11319, 11372, 11397, 11419, 11535, 12684, 12742, 12769, 12816, 12838, 12915, 12933, 12991, 12999, 13067, 13101, 13123, 13143, 13150, 13164, 13203, 13275, 13398, 13459, 13883, 14523, 15012, 15198, 15210, 15240, 15613, 15617, 15769, 15783, 16137, 16187 ],
    "fillerIds" : [ 5145, 10294, 11143, 11325, 11390, 11548, 11717, 11726, 11890, 11963, 12023, 13085, 13493, 13586, 13729, 13760, 13773, 13975, 14023, 14281, 14385, 14457, 15946, 16056, 16104, 16168, 16234, 16423, 16500, 16569, 18726 ]
  }, {
    "name" : "c6",
    "version" : "PRDAPTSOC-058-003",
    "masterBackground" : false,
    "slitlets" : [ {
      "q" : 1,
      "d" : 27,
      "s" : 171
    }, {
      "q" : 1,
      "d" : 35,
      "s" : 53
    }, {
      "q" : 2,
      "d" : 38,
      "s" : 80
    }, {
      "q" : 2,
      "d" : 55,
      "s" : 90
    }, {
      "q" : 2,
      "d" : 61,
      "s" : 14
    }, {
      "q" : 1,
      "d" : 63,
      "s" : 151
    }, {
      "q" : 1,
      "d" : 90,
      "s" : 76
    }, {
      "q" : 1,
      "d" : 93,
      "s" : 40
    }, {
      "q" : 2,
      "d" : 102,
      "s" : 88
    }, {
      "q" : 2,
      "d" : 112,
      "s" : 54
    }, {
      "q" : 2,
      "d" : 119,
      "s" : 78
    }, {
      "q" : 2,
      "d" : 124,
      "s" : 66
    }, {
      "q" : 1,
      "d" : 131,
      "s" : 99
    }, {
      "q" : 1,
      "d" : 135,
      "s" : 22
    }, {
      "q" : 2,
      "d" : 135,
      "s" : 140
    }, {
      "q" : 2,
      "d" : 137,
      "s" : 86
    }, {
      "q" : 2,
      "d" : 146,
      "s" : 124
    }, {
      "q" : 1,
      "d" : 149,
      "s" : 114
    }, {
      "q" : 1,
      "d" : 153,
      "s" : 51
    }, {
      "q" : 1,
      "d" : 154,
      "s" : 65
    }, {
      "q" : 1,
      "d" : 157,
      "s" : 153
    }, {
      "q" : 1,
      "d" : 161,
      "s" : 137
    }, {
      "q" : 1,
      "d" : 162,
      "s" : 87
    }, {
      "q" : 2,
      "d" : 162,
      "s" : 82
    }, {
      "q" : 2,
      "d" : 163,
      "s" : 56
    }, {
      "q" : 2,
      "d" : 166,
      "s" : 150
    }, {
      "q" : 1,
      "d" : 170,
      "s" : 47
    }, {
      "q" : 2,
      "d" : 172,
      "s" : 37
    }, {
      "q" : 2,
      "d" : 172,
      "s" : 129
    }, {
      "q" : 1,
      "d" : 176,
      "s" : 79
    }, {
      "q" : 2,
      "d" : 191,
      "s" : 84
    }, {
      "q" : 2,
      "d" : 203,
      "s" : 71
    }, {
      "q" : 1,
      "d" : 206,
      "s" : 123
    }, {
      "q" : 2,
      "d" : 212,
      "s" : 44
    }, {
      "q" : 2,
      "d" : 213,
      "s" : 126
    }, {
      "q" : 2,
      "d" : 220,
      "s" : 60
    }, {
      "q" : 2,
      "d" : 224,
      "s" : 11
    }, {
      "q" : 1,
      "d" : 231,
      "s" : 96
    }, {
      "q" : 2,
      "d" : 239,
      "s" : 52
    }, {
      "q" : 2,
      "d" : 240,
      "s" : 46
    }, {
      "q" : 1,
      "d" : 243,
      "s" : 17
    }, {
      "q" : 2,
      "d" : 247,
      "s" : 76
    }, {
      "q" : 2,
      "d" : 247,
      "s" : 122
    }, {
      "q" : 1,
      "d" : 254,
      "s" : 167
    }, {
      "q" : 2,
      "d" : 267,
      "s" : 22
    }, {
      "q" : 2,
      "d" : 280,
      "s" : 8
    }, {
      "q" : 2,
      "d" : 281,
      "s" : 103
    }, {
      "q" : 1,
      "d" : 286,
      "s" : 54
    }, {
      "q" : 2,
      "d" : 302,
      "s" : 34
    }, {
      "q" : 2,
      "d" : 308,
      "s" : 156
    }, {
      "q" : 2,
      "d" : 348,
      "s" : 111
    }, {
      "q" : 1,
      "d" : 353,
      "s" : 112
    }, {
      "q" : 3,
      "d" : 26,
      "s" : 117
    }, {
      "q" : 3,
      "d" : 35,
      "s" : 148
    }, {
      "q" : 4,
      "d" : 42,
      "s" : 136
    }, {
      "q" : 3,
      "d" : 52,
      "s" : 58
    }, {
      "q" : 4,
      "d" : 52,
      "s" : 145
    }, {
      "q" : 3,
      "d" : 87,
      "s" : 121
    }, {
      "q" : 3,
      "d" : 91,
      "s" : 19
    }, {
      "q" : 4,
      "d" : 120,
      "s" : 50
    }, {
      "q" : 4,
      "d" : 135,
      "s" : 25
    }, {
      "q" : 4,
      "d" : 138,
      "s" : 138
    }, {
      "q" : 4,
      "d" : 139,
      "s" : 99
    }, {
      "q" : 4,
      "d" : 142,
      "s" : 158
    }, {
      "q" : 4,
      "d" : 150,
      "s" : 108
    }, {
      "q" : 3,
      "d" : 159,
      "s" : 56
    }, {
      "q" : 3,
      "d" : 167,
      "s" : 141
    }, {
      "q" : 4,
      "d" : 172,
      "s" : 154
    }, {
      "q" : 3,
      "d" : 207,
      "s" : 127
    }, {
      "q" : 4,
      "d" : 235,
      "s" : 6
    }, {
      "q" : 4,
      "d" : 242,
      "s" : 92
    }, {
      "q" : 4,
      "d" : 249,
      "s" : 114
    }, {
      "q" : 4,
      "d" : 279,
      "s" : 68
    }, {
      "q" : 3,
      "d" : 295,
      "s" : 94
    }, {
      "q" : 4,
      "d" : 295,
      "s" : 19
    }, {
      "q" : 4,
      "d" : 304,
      "s" : 3
    }, {
      "q" : 4,
      "d" : 348,
      "s" : 63
    }, {
      "q" : 4,
      "d" : 351,
      "s" : 96
    }, {
      "q" : 4,
      "d" : 355,
      "s" : 74
    }, {
      "q" : 2,
      "d" : 164,
      "s" : 64
    }, {
      "q" : 2,
      "d" : 253,
      "s" : 101
    }, {
      "q" : 1,
      "d" : 114,
      "s" : 102
    }, {
      "q" : 1,
      "d" : 35,
      "s" : 78
    }, {
      "q" : 2,
      "d" : 87,
      "s" : 39
    }, {
      "q" : 1,
      "d" : 232,
      "s" : 119
    }, {
      "q" : 2,
      "d" : 323,
      "s" : 69
    }, {
      "q" : 3,
      "d" : 103,
      "s" : 49
    }, {
      "q" : 3,
      "d" : 286,
      "s" : 116
    }, {
      "q" : 3,
      "d" : 78,
      "s" : 85
    }, {
      "q" : 3,
      "d" : 150,
      "s" : 73
    }, {
      "q" : 1,
      "d" : 359,
      "s" : 125
    }, {
      "q" : 4,
      "d" : 350,
      "s" : 94
    }, {
      "q" : 2,
      "d" : 106,
      "s" : 120
    }, {
      "q" : 1,
      "d" : 17,
      "s" : 147
    }, {
      "q" : 2,
      "d" : 267,
      "s" : 21
    }, {
      "q" : 1,
      "d" : 256,
      "s" : 37
    }, {
      "q" : 1,
      "d" : 269,
      "s" : 63
    }, {
      "q" : 1,
      "d" : 223,
      "s" : 110
    }, {
      "q" : 2,
      "d" : 347,
      "s" : 106
    }, {
      "q" : 3,
      "d" : 259,
      "s" : 135
    }, {
      "q" : 3,
      "d" : 37,
      "s" : 45
    }, {
      "q" : 3,
      "d" : 191,
      "s" : 14
    }, {
      "q" : 3,
      "d" : 214,
      "s" : 33
    }, {
      "q" : 1,
      "d" : 121,
      "s" : 169
    }, {
      "q" : 1,
      "d" : 52,
      "s" : 31
    }, {
      "q" : 2,
      "d" : 80,
      "s" : 134
    }, {
      "q" : 1,
      "d" : 89,
      "s" : 27
    }, {
      "q" : 1,
      "d" : 164,
      "s" : 105
    }, {
      "q" : 1,
      "d" : 249,
      "s" : 159
    }, {
      "q" : 1,
      "d" : 255,
      "s" : 165
    }, {
      "q" : 3,
      "d" : 112,
      "s" : 91
    }, {
      "q" : 3,
      "d" : 336,
      "s" : 71
    }, {
      "q" : 3,
      "d" : 260,
      "s" : 62
    } ],
    "exposures" : [ {
      "name" : "c6e1",
      "gratingFilter" : "G140H_F100LP",
      "msaSlitlet" : "ONE_SHUTTER",
      "ra" : 23.50352666128983,
      "dec" : 30.758943172983237,
      "sourceIds" : [ 2178, 3462, 3476, 3532, 3560, 3582, 3619, 3687, 4720, 4995, 5120, 5140, 5145, 5529, 10294, 10503, 10506, 10558, 10564, 10588, 10630, 10642, 10698, 10747, 10763, 10766, 10798, 10823, 10825, 10827, 10836, 10837, 10850, 10877, 10884, 10897, 10924, 10977, 10994, 11016, 11051, 11143, 11148, 11193, 11197, 11232, 11319, 11325, 11372, 11390, 11397, 11419, 11535, 11548, 11717, 11726, 11890, 11963, 12023, 12684, 12742, 12769, 12816, 12838, 12915, 12933, 12991, 12999, 13067, 13085, 13101, 13123, 13143, 13150, 13164, 13203, 13275, 13398, 13459, 13493, 13586, 13729, 13760, 13773, 13793, 13883, 13975, 14023, 14281, 14385, 14457, 14523, 15012, 15198, 15210, 15240, 15613, 15617, 15769, 15783, 15946, 16056, 16104, 16137, 16168, 16187, 16234, 16423, 16493, 16500, 16562, 16569, 18726 ]
    } ],
    "primaryIds" : [ 2178, 3462, 3476, 3532, 3560, 3582, 3619, 3687, 4720, 4995, 5120, 5140, 5529, 10503, 10506, 10558, 10564, 10588, 10630, 10642, 10698, 10747, 10763, 10766, 10798, 10823, 10825, 10827, 10836, 10837, 10850, 10877, 10884, 10897, 10924, 10977, 10994, 11016, 11051, 11148, 11193, 11197, 11232, 11319, 11372, 11397, 11419, 11535, 12684, 12742, 12769, 12816, 12838, 12915, 12933, 12991, 12999, 13067, 13101, 13123, 13143, 13150, 13164, 13203, 13275, 13398, 13459, 13883, 14523, 15012, 15198, 15210, 15240, 15613, 15617, 15769, 15783, 16137, 16187 ],
    "fillerIds" : [ 5145, 10294, 11143, 11325, 11390, 11548, 11717, 11726, 11890, 11963, 12023, 13085, 13493, 13586, 13729, 13760, 13773, 13793, 13975, 14023, 14281, 14385, 14457, 15946, 16056, 16104, 16168, 16234, 16423, 16493, 16500, 16562, 16569, 18726 ]
  } ],
  "stats" : [ {
    "name" : "s0",
    "score" : 23.0,
    "numberOfConfigurations" : 6,
    "numberOfTargets" : 138,
    "duration" : 33.595,
    "totalDuration" : 33.595
  } ],
  "plannerSpecification" : {
    "gratingSpecification" : {
      "allowContamination" : false,
      "gratings" : [ "G140H_F100LP" ],
      "multiplexingMinimum" : {
        "empty" : true,
        "present" : false
      },
      "multiplexLimit" : null
    },
    "candidates" : {
      "primaries" : "target",
      "fillers" : "filler"
    },
    "slitSpecification" : {
      "sweetSpot" : "PERCENT_75",
      "slitlet" : "ONE_SHUTTER"
    },
    "pointingSpecification" : {
      "partiallyCompletedSources" : false,
      "ditherType" : "FIXED",
      "minimumDitherPoints" : null,
      "numberOfNods" : 1,
      "fixedDitherOffsets" : [ {
        "spatial" : 0,
        "dispersion" : 0
      }, {
        "spatial" : 0,
        "dispersion" : 1
      }, {
        "spatial" : 1,
        "dispersion" : 2
      }, {
        "spatial" : 1,
        "dispersion" : 5
      }, {
        "spatial" : 2,
        "dispersion" : 6
      }, {
        "spatial" : 2,
        "dispersion" : 7
      } ],
      "shouldNod" : false
    },
    "searchGridSpecification" : {
      "searchAreaCenter" : {
        "ra" : 23.496074692599027,
        "dec" : 30.782224382402873
      },
      "searchAreaWidth" : 644.5100727305394,
      "searchAreaHeight" : 597.4320149983027,
      "searchStepSize" : 30.0,
      "searchArea" : {
        "center" : {
          "x" : 84585.8685,
          "y" : 110816.01
        },
        "corners" : [ {
          "ra" : 23.3894683477378,
          "dec" : 30.698891666666665
        }, {
          "ra" : 23.60286570854439,
          "dec" : 30.865558333333333
        }, {
          "ra" : 23.3894683477378,
          "dec" : 30.865558333333333
        }, {
          "ra" : 23.60286570854439,
          "dec" : 30.698891666666665
        } ],
        "xlength" : 660.0,
        "ylength" : 600.0,
        "offsetToBottomCorner" : {
          "x" : -330.0,
          "y" : -300.0
        },
        "width" : 660.0,
        "height" : 600.0
      }
    },
    "searchParameters" : {
      "spectralOverlapShutterOffsetMap" : "JWST_NIRSPEC_G140H",
      "spectralOverlapThreshold" : 1.5,
      "numberOfConfigurations" : 6,
      "ignoreStuckOpen" : false,
      "useWeights" : false,
      "enableMonteCarlo" : false,
      "monteCarloShuffles" : 10
    },
    "planAngle" : 210.0,
    "planName" : "M33-topright-golden",
    "theta" : {
      "empty" : true,
      "present" : false
    }
  }
}